{
  "format": "scripture burrito",
  "meta": {
    "version": "1.0.0",
    "category": "source",
    "generator": {
      "softwareName": "Scribe",
      "softwareVersion": "0.5.11",
      "userName": "liju"
    },
    "defaultLocale": "en",
    "dateCreated": "2024-09-04T10:10:01+05:30",
    "normalization": "NFC"
  },
  "idAuthorities": {
    "scribe": {
      "id": "http://www.scribe.bible",
      "name": {
        "en": "Scribe application"
      }
    }
  },
  "identification": {
    "primary": {
      "scribe": {
        "79ed939e-ae42-5133-ba15-c5c58add79bc": {
          "revision": "2",
          "timestamp": "2024-09-04T10:10:01+05:30"
        }
      }
    },
    "name": {
      "en": "Test 1"
    },
    "abbreviation": {
      "en": "T1"
    }
  },
  "confidential": false,
  "languages": [
    {
      "tag": "en",
      "name": {
        "en": "English"
      },
      "scriptDirection": "ltr"
    }
  ],
  "type": {
    "flavorType": {
      "name": "scripture",
      "flavor": {
        "name": "textTranslation",
        "projectType": "standard",
        "translationType": "firstTranslation",
        "audience": "common",
        "usfmVersion": "3.0.2"
      },
      "currentScope": {
        "EXO": [],
        "PSA": [],
        "MAT": [],
        "DAN": [],
        "HAB": [],
        "ZEP": [],
        "JAS": [],
        "2CO": [],
        "ACT": [],
        "JHN": []
      }
    }
  },
  "copyright": {
    "licenses": [
      {
        "ingredient": "license.md"
      }
    ]
  },
  "localizedNames": {
    "GEN": {
      "short": {
        "en": "Genesis"
      },
      "abbr": {
        "en": "Genesis"
      },
      "long": {
        "en": "The First Book of Moses, Commonly Called Genesis"
      }
    },
    "EXO": {
      "short": {
        "en": "Exodus"
      },
      "abbr": {
        "en": "Exodus"
      },
      "long": {
        "en": "The Second Book of Mosis, Commonly Called Exodus"
      }
    },
    "PSA": {
      "short": {
        "en": "Psalms"
      },
      "abbr": {
        "en": "Psalm"
      },
      "long": {
        "en": "The Psalms"
      }
    },
    "MAT": {
      "short": {
        "en": "Matthew"
      },
      "abbr": {
        "en": "Matthew"
      },
      "long": {
        "en": "The Good News According to Matthew"
      }
    },
    "DAN": {
      "short": {
        "en": "Daniel"
      },
      "abbr": {
        "en": "Daniel"
      },
      "long": {
        "en": "The Book of Daniel"
      }
    },
    "HAB": {
      "short": {
        "en": "Habakkuk"
      },
      "abbr": {
        "en": "Habakkuk"
      },
      "long": {
        "en": "The Book of Habakkuk"
      }
    },
    "ZEP": {
      "short": {
        "en": "Zephaniah"
      },
      "abbr": {
        "en": "Zephaniah"
      },
      "long": {
        "en": "The Book of Zephaniah"
      }
    },
    "JAS": {
      "short": {
        "en": "James"
      },
      "abbr": {
        "en": "James"
      },
      "long": {
        "en": "The Letter from James"
      }
    },
    "2CO": {
      "short": {
        "en": "2 Corinthians"
      },
      "abbr": {
        "en": "2 Corinthians"
      },
      "long": {
        "en": "Paul’s Second Letter to the Corinthians"
      }
    },
    "ACT": {
      "short": {
        "en": "Acts"
      },
      "abbr": {
        "en": "Acts"
      },
      "long": {
        "en": "The Acts of the Apostles"
      }
    },
    "JHN": {
      "short": {
        "en": "John"
      },
      "abbr": {
        "en": "John"
      },
      "long": {
        "en": "The Good News According to John"
      }
    }
  },
  "ingredients": {
    "ingredients/GEN.sfm": {
      "checksum": {
        "md5": "e7b2ca4ba7eb29bc57c36bd2e524f92c"
      },
      "mimeType": "text/x-usfm",
      "size": 15343,
      "scope": {
        "GEN": []
      }
    },
    "ingredients/EXO.sfm": {
      "checksum": {
        "md5": "bdb9c8c2932bec4cdbdd7cd66ba77f16"
      },
      "mimeType": "text/x-usfm",
      "size": 12143,
      "scope": {
        "EXO": []
      }
    },
    "ingredients/PSA.sfm": {
      "checksum": {
        "md5": "550f1a662c08782d671770f8b527f525"
      },
      "mimeType": "text/x-usfm",
      "size": 24858,
      "scope": {
        "PSA": []
      }
    },
    "ingredients/MAT.usfm": {
      "checksum": {
        "md5": "35a8710ba640c2f7c7613f9bc4dde4a7"
      },
      "mimeType": "text/x-usfm",
      "size": 10723,
      "scope": {
        "MAT": []
      }
    },
    "ingredients/DAN.usfm": {
      "checksum": {
        "md5": "34595c2bd457376c85533091eb32fb58"
      },
      "mimeType": "text/x-usfm",
      "size": 3583,
      "scope": {
        "DAN": []
      }
    },
    "ingredients/HAB.usfm": {
      "checksum": {
        "md5": "ed1a23dc9098c6cd19b2734658c0df98"
      },
      "mimeType": "text/x-usfm",
      "size": 579,
      "scope": {
        "HAB": []
      }
    },
    "ingredients/ZEP.usfm": {
      "checksum": {
        "md5": "8c4a16e4e85199511cdb75530eb278cb"
      },
      "mimeType": "text/x-usfm",
      "size": 549,
      "scope": {
        "ZEP": []
      }
    },
    "ingredients/JAS.usfm": {
      "checksum": {
        "md5": "631a4df9ff07b79bfb66afe08cbd9ddd"
      },
      "mimeType": "text/x-usfm",
      "size": 1097,
      "scope": {
        "JAS": []
      }
    },
    "ingredients/2CO.usfm": {
      "checksum": {
        "md5": "bab57aad024304839ad7e0b1423aaca3"
      },
      "mimeType": "text/x-usfm",
      "size": 2583,
      "scope": {
        "2CO": []
      }
    },
    "ingredients/ACT.sfm": {
      "checksum": {
        "md5": "2f47fa1b2f3490afe5f8649718098f44"
      },
      "mimeType": "text/x-usfm",
      "size": 10083,
      "scope": {
        "ACT": []
      }
    },
    "ingredients/MRK.sfm": {
      "checksum": {
        "md5": "bdb9c8c2932bec4cdbdd7cd66ba77f16"
      },
      "mimeType": "text/x-usfm",
      "size": 12143,
      "scope": {
        "MRK": []
      }
    },
    "ingredients/JHN.usfm": {
      "checksum": {
        "md5": "b8275bf1847da797a23f6c192eb8d7f6"
      },
      "mimeType": "text/x-usfm",
      "size": 8803,
      "scope": {
        "JHN": []
      }
    },
    "ingredients/versification.json": {
      "checksum": {
        "md5": "b563953d1cb9ded9f4c2a6757b388064"
      },
      "mimeType": "application/json",
      "size": 14696,
      "role": "x-versification"
    },
    "ingredients/license.md": {
      "checksum": {
        "md5": "0bf7ef1533f6486c8362dcb8bc19bdd1"
      },
      "mimeType": "text/md",
      "size": 18535,
      "role": "x-licence"
    },
    "ingredients/scribe-settings.json": {
      "checksum": {
        "md5": "708639ec552b38a5242fbd9dd162511b"
      },
      "mimeType": "application/json",
      "size": 301,
      "role": "x-scribe"
    },
    "audio/ingredients/3JN/1/1.wav": {
      "checksum": {
        "md5": "8997e47f2f062cceb54aa7b1ceeba35b"
      },
      "mimeType": "audio/mp3",
      "size": 14093,
      "scope": {
        "3JN": ["1:1"]
      }
    },
    "audio/ingredients/3JN/1/2.wav": {
      "checksum": {
        "md5": "8997e47f2f062cceb54aa7b1ceeba35b"
      },
      "mimeType": "audio/mp3",
      "size": 14093,
      "scope": {
        "3JN": ["1:2"]
      }
    },
    "audio/ingredients/3JN/1/5.wav": {
      "checksum": {
        "md5": "8997e47f2f062cceb54aa7b1ceeba35b"
      },
      "mimeType": "audio/mp3",
      "size": 14093,
      "scope": {
        "3JN": ["1:5"]
      }
    },
    "audio/ingredients/3JN/1/10.wav": {
      "checksum": {
        "md5": "8997e47f2f062cceb54aa7b1ceeba35b"
      },
      "mimeType": "audio/mp3",
      "size": 14093,
      "scope": {
        "3JN": ["1:10"]
      }
    },
    "audio/ingredients/3JN/1/3.wav": {
      "checksum": {
        "md5": "8997e47f2f062cceb54aa7b1ceeba35b"
      },
      "mimeType": "audio/mp3",
      "size": 14093,
      "scope": {
        "3JN": ["1:3"]
      }
    },
    "audio/ingredients/3JN/1/6.wav": {
      "checksum": {
        "md5": "8997e47f2f062cceb54aa7b1ceeba35b"
      },
      "mimeType": "audio/mp3",
      "size": 14093,
      "scope": {
        "3JN": ["1:6"]
      }
    }
  }
}
